<?xml version="1.0" encoding="Windows-1252"?>
<AIdatabase xmlns:xsi="http://www.w3.org/2001/XMLSchema-instance" xmlns:xsd="http://www.w3.org/2001/XMLSchema">
  <AIList>
    <AIEntry>
      <ID>4</ID>
      <originZone>7</originZone>
      <state>0</state>
      <position>
        <x>67.44049</x>
        <y>0.8000001</y>
        <z>162.7032</z>
      </position>
      <rotation>
        <x>0</x>
        <y>70.7201843</y>
        <z>0</z>
      </rotation>
    </AIEntry>
    <AIEntry>
      <ID>4</ID>
      <originZone>7</originZone>
      <state>0</state>
      <position>
        <x>67.44049</x>
        <y>0.8000001</y>
        <z>162.7032</z>
      </position>
      <rotation>
        <x>0</x>
        <y>70.7201843</y>
        <z>0</z>
      </rotation>
    </AIEntry>
    <AIEntry>
      <ID>4</ID>
      <originZone>11</originZone>
      <state>0</state>
      <position>
        <x>82.29988</x>
        <y>0.7999991</y>
        <z>198.858719</z>
      </position>
      <rotation>
        <x>0</x>
        <y>145.429245</y>
        <z>0</z>
      </rotation>
    </AIEntry>
    <AIEntry>
      <ID>4</ID>
      <originZone>11</originZone>
      <state>0</state>
      <position>
        <x>82.29988</x>
        <y>0.7999991</y>
        <z>198.858719</z>
      </position>
      <rotation>
        <x>0</x>
        <y>145.429245</y>
        <z>0</z>
      </rotation>
    </AIEntry>
    <AIEntry>
      <ID>5</ID>
      <originZone>14</originZone>
      <state>0</state>
      <position>
        <x>89.4335556</x>
        <y>0.8</y>
        <z>218.77327</z>
      </position>
      <rotation>
        <x>0</x>
        <y>120.431892</y>
        <z>0</z>
      </rotation>
    </AIEntry>
    <AIEntry>
      <ID>5</ID>
      <originZone>14</originZone>
      <state>0</state>
      <position>
        <x>89.4335556</x>
        <y>0.8</y>
        <z>218.77327</z>
      </position>
      <rotation>
        <x>0</x>
        <y>120.431892</y>
        <z>0</z>
      </rotation>
    </AIEntry>
    <AIEntry>
      <ID>13</ID>
      <originZone>14</originZone>
      <state>1</state>
      <position>
        <x>51.9115</x>
        <y>0.8</y>
        <z>219.936874</z>
      </position>
      <rotation>
        <x>0</x>
        <y>9.536343</y>
        <z>0</z>
      </rotation>
    </AIEntry>
    <AIEntry>
      <ID>13</ID>
      <originZone>14</originZone>
      <state>1</state>
      <position>
        <x>51.9115</x>
        <y>0.8</y>
        <z>219.936874</z>
      </position>
      <rotation>
        <x>0</x>
        <y>9.536343</y>
        <z>0</z>
      </rotation>
    </AIEntry>
    <AIEntry>
      <ID>23</ID>
      <originZone>9</originZone>
      <state>0</state>
      <position>
        <x>57.85563</x>
        <y>0.8</y>
        <z>177.622574</z>
      </position>
      <rotation>
        <x>0</x>
        <y>79.76081</y>
        <z>0</z>
      </rotation>
    </AIEntry>
  </AIList>
</AIdatabase>